pdk8s/__init__.py
pdk8s/chart_cli.py
pdk8s/cli.py
pdk8s/cookiecutter/cookiecutter.json
pdk8s/cookiecutter/{{cookiecutter.slug}}/.gitignore
pdk8s/cookiecutter/{{cookiecutter.slug}}/chart.py
pdk8s/gen/__init__.py
pdk8s/gen/io/__init__.py
pdk8s/gen/io/k8s/__init__.py
pdk8s/gen/io/k8s/api/__init__.py
pdk8s/gen/io/k8s/api/admissionregistration/__init__.py
pdk8s/gen/io/k8s/api/admissionregistration/v1.py
pdk8s/gen/io/k8s/api/admissionregistration/v1beta1.py
pdk8s/gen/io/k8s/api/apps/__init__.py
pdk8s/gen/io/k8s/api/apps/v1.py
pdk8s/gen/io/k8s/api/apps/v1beta1.py
pdk8s/gen/io/k8s/api/apps/v1beta2.py
pdk8s/gen/io/k8s/api/auditregistration/__init__.py
pdk8s/gen/io/k8s/api/auditregistration/v1alpha1.py
pdk8s/gen/io/k8s/api/authentication/__init__.py
pdk8s/gen/io/k8s/api/authentication/v1.py
pdk8s/gen/io/k8s/api/authentication/v1beta1.py
pdk8s/gen/io/k8s/api/authorization/__init__.py
pdk8s/gen/io/k8s/api/authorization/v1.py
pdk8s/gen/io/k8s/api/authorization/v1beta1.py
pdk8s/gen/io/k8s/api/autoscaling/__init__.py
pdk8s/gen/io/k8s/api/autoscaling/v1.py
pdk8s/gen/io/k8s/api/autoscaling/v2beta1.py
pdk8s/gen/io/k8s/api/autoscaling/v2beta2.py
pdk8s/gen/io/k8s/api/batch/__init__.py
pdk8s/gen/io/k8s/api/batch/v1.py
pdk8s/gen/io/k8s/api/batch/v1beta1.py
pdk8s/gen/io/k8s/api/batch/v2alpha1.py
pdk8s/gen/io/k8s/api/certificates/__init__.py
pdk8s/gen/io/k8s/api/certificates/v1beta1.py
pdk8s/gen/io/k8s/api/coordination/__init__.py
pdk8s/gen/io/k8s/api/coordination/v1.py
pdk8s/gen/io/k8s/api/coordination/v1beta1.py
pdk8s/gen/io/k8s/api/core/__init__.py
pdk8s/gen/io/k8s/api/core/v1.py
pdk8s/gen/io/k8s/api/discovery/__init__.py
pdk8s/gen/io/k8s/api/discovery/v1alpha1.py
pdk8s/gen/io/k8s/api/events/__init__.py
pdk8s/gen/io/k8s/api/events/v1beta1.py
pdk8s/gen/io/k8s/api/extensions/__init__.py
pdk8s/gen/io/k8s/api/extensions/v1beta1.py
pdk8s/gen/io/k8s/api/networking/__init__.py
pdk8s/gen/io/k8s/api/networking/v1.py
pdk8s/gen/io/k8s/api/networking/v1beta1.py
pdk8s-0.2.2.dist-info/entry_points.txt
pdk8s-0.2.2.dist-info/LICENSE
pdk8s-0.2.2.dist-info/WHEEL
pdk8s-0.2.2.dist-info/METADATA
pdk8s-0.2.2.dist-info/RECORD
