Metadata-Version: 2.1
Name: pdk8s
Version: 0.2.2
Summary: 
License: Apache-2.0
Author: Florian Ludwig
Author-email: f.ludwig@greyrook.com
Requires-Python: >=3.7,<4.0
Classifier: License :: OSI Approved :: Apache Software License
Classifier: Programming Language :: Python :: 3
Classifier: Programming Language :: Python :: 3.7
Classifier: Programming Language :: Python :: 3.8
Requires-Dist: click (==7.1.2)
Requires-Dist: cookiecutter (==1.7.2)
Requires-Dist: datamodel-code-generator (>=0.5.9,<0.6.0)
Requires-Dist: pydantic (==1.5.1)
Requires-Dist: pyyaml (==5.3.1)
Requires-Dist: setuptools (==47.1.1)
